gemini_agent_helper-0.1.1.dist-info/licenses/LICENSE
gemini_helper/__init__.py
gemini_helper/core.py
gemini_agent_helper-0.1.1.dist-info/METADATA
gemini_agent_helper-0.1.1.dist-info/WHEEL
gemini_agent_helper-0.1.1.dist-info/top_level.txt
gemini_agent_helper-0.1.1.dist-info/RECORD
