Metadata-Version: 2.4
Name: gemini-agent-helper
Version: 0.1.1
Summary: Add your description here
Home-page: https://github.com/huriyasyed/gemini-helper
Author: Huriya Syed
Author-email: huriyasyed462@gmail.com
Requires-Python: >=3.8
License-File: LICENSE
Requires-Dist: openai-agents>=0.0.17
Requires-Dist: python-dotenv>=1.1.0
Requires-Dist: runner>=1.1
Requires-Dist: setuptools>=80.9.0
Requires-Dist: wheel>=0.45.1
Dynamic: author
Dynamic: author-email
Dynamic: home-page
Dynamic: license-file
Dynamic: requires-python
